{
  "unversionedId": "react/using-react",
  "id": "react/using-react",
  "isDocsHomePage": false,
  "title": "Using React",
  "description": "To use the React environment, set it in the workspace.jsonc configuration file. React can only be configured using the 'variants' config API.",
  "source": "@site/docs/react/02-using-react.md",
  "slug": "/react/using-react",
  "permalink": "/docs/react/using-react",
  "editUrl": "https://github.com/teambit/docs/edit/harmony/docs/react/02-using-react.md",
  "version": "current",
  "sidebar": "docs",
  "previous": {
    "title": "Overview",
    "permalink": "/docs/react/overview"
  },
  "next": {
    "title": "Extending React",
    "permalink": "/docs/react/extending-react"
  }
}