{
  "docs": {
    "Basics": [
        "overview",
        "concepts",
        "quick-start",
        "best-practices",
        "getting-help"
    ],
    "Tutorials": [
        "tutorials/bit-react-tutorial",
        "tutorials/bit-angular-tutorial",
        "tutorials/bit-nodejs-tutorial"
    ],
    "Setup": [
        "installation",
        "setup-authentication",
        "initializing-bit",
        "remote-collection",
        "conf-files",
        "handling-errors",
        "authentication-issues",
        "conf-analytics"
    ],
    "Components Workflow": [
      {
        "type": "subcategory",
        "label": "Add & Isolate Components",
        "ids": [
          "add-and-isolate-component",
          "component-dependencies",
          "tracking-dependencies",
          "manage-component-files",
          "troubleshooting-isolating"
        ]
      },
        "building-components",
        "testing-components",
        "tag-component-version",
        "documenting-components",
        "organizing-components",
        {
        "type": "subcategory",
        "label": "Share Components to Bit.dev",
        "ids": [
          "organizing-components",
          "removing-components",
          "installing-components"
        ]
      },
      {
        "type": "subcategory",
        "label": "Sourcing Components",
        "ids": [
          "sourcing-components",
          "modifying-sourced-components",
          "update-dependencies",
          "updating-sourced-components",
          "merge-changes"
        ]
      },
        "workspace-statuses"
    ],
    "Extending Bit": [
        "ext-concepts",
        "ext-using-extensions",
        "ext-developing-extensions",
        "ext-compiling",
        "ext-testing"
    ],
    "Guides": [
        "react-guidelines",
        "angular-guidelines",
        "ci",
        "bit-server"
    ],
    "bit.dev": [
        "bitsrc-component-ci",
        "my-account",
        "bitsrc-plans",
        "bitsrc-security",
        "bitdev-permissions",
        "bitdev-sla"
    ],
    "Reference": [
        "conf-config",
        "conf-bit-json",
        {
          "type": "subcategory",
          "label": "CLI Reference",
          "ids": [
            "cli/cli-add",
            "cli/cli-build",
            "cli/cli-checkout",
            "cli/cli-clear-cache",
            "cli/cli-config",
            "cli/cli-deprecate",
            "cli/cli-diff",
            "cli/cli-doctor",
            "cli/cli-eject",
            "cli/cli-export",
            "cli/cli-import",
            "cli/cli-install",
            "cli/cli-init",
            "cli/cli-link",
            "cli/cli-list",
            "cli/cli-log",
            "cli/cli-login",
            "cli/cli-logout",
            "cli/cli-merge",
            "cli/cli-move",
            "cli/cli-remote",
            "cli/cli-remove",
            "cli/cli-show",
            "cli/cli-status",
            "cli/cli-tag",
            "cli/cli-test",
            "cli/cli-untag",
            "cli/cli-untrack",
            "cli/cli-watch"
          ]
        }
    ]
  },
  "whybit?": {
    "Why Bit?": [
    "whybit/why-bit",
    "whybit/for-teams",
    "whybit/for-libs"
  ]
}
}
